fabric_mgmt_cli/__init__.py
fabric_mgmt_cli/managecli/__init__.py
fabric_mgmt_cli/managecli/command.py
fabric_mgmt_cli/managecli/config_processor.py
fabric_mgmt_cli/managecli/configuration.py
fabric_mgmt_cli/managecli/kafka_processor.py
fabric_mgmt_cli/managecli/manage_command.py
fabric_mgmt_cli/managecli/managecli.py
fabric_mgmt_cli/managecli/show_command.py
fabric_mgmt_cli/managecli/net/__init__.py
fabric_mgmt_cli/managecli/net/commands.py
fabric_mgmt_cli/managecli/net/nso.py
fabric_mgmt_cli/managecli/net/resources.py
fabric_mgmt_cli/managecli/net/services.py
fabric_mgmt_cli/managecli/net/util.py
fabric_mgmt_cli/managecli/test/__init__.py
fabric_mgmt_cli/managecli/test/config.yml
fabric_mgmt_cli/managecli/test/test_managecli.py
fabric_mgmt_cli-1.7.0.dist-info/entry_points.txt
fabric_mgmt_cli-1.7.0.dist-info/LICENSE
fabric_mgmt_cli-1.7.0.dist-info/WHEEL
fabric_mgmt_cli-1.7.0.dist-info/METADATA
fabric_mgmt_cli-1.7.0.dist-info/RECORD
