Metadata-Version: 2.1
Name: fabric-mgmt-cli
Version: 1.7.0
Summary: FABRIC Management CLI
Keywords: Swagger,Fabric Management Cli
Author-email: Komal Thareja <kthare10@renci.org>
Requires-Python: >=3.9
Classifier: Programming Language :: Python :: 3
Classifier: License :: OSI Approved :: MIT License
Classifier: Operating System :: OS Independent
Requires-Dist: click==7.1.2
Requires-Dist: pytest==7.1.1
Requires-Dist: fabric-cf==1.7.0
Requires-Dist: ansible
Requires-Dist: coverage>=4.0.3 ; extra == "test"
Requires-Dist: nose>=1.3.7 ; extra == "test"
Requires-Dist: pluggy>=0.3.1 ; extra == "test"
Requires-Dist: py>=1.4.31 ; extra == "test"
Requires-Dist: randomize>=0.13 ; extra == "test"
Project-URL: Home, https://fabric-testbed.net/
Project-URL: Sources, https://github.com/fabric-testbed/ManagementCli
Provides-Extra: test
